nb2mail/__init__.py
nb2mail/templates/mail.tpl
nb2mail-0.8.dist-info/METADATA
nb2mail-0.8.dist-info/WHEEL
nb2mail-0.8.dist-info/entry_points.txt
nb2mail-0.8.dist-info/top_level.txt
nb2mail-0.8.dist-info/RECORD
